README.rst
anti_lib.py
setup.py
anti_lib_progs/__init__.py
anti_lib_progs/anti_lib.py
anti_lib_progs/barrel.py
anti_lib_progs/eq_antherm.py
anti_lib_progs/geodesic.py
anti_lib_progs/gold_bowtie.py
anti_lib_progs/lamella.py
anti_lib_progs/lat_grid.py
anti_lib_progs/njitterbug.py
anti_lib_progs/njohnson.py
anti_lib_progs/packer.py
anti_lib_progs/pentabelt.py
anti_lib_progs/proj_dome.py
anti_lib_progs/rhombic_3band.py
anti_lib_progs/ring_place.py
anti_lib_progs/rotegrity_models.py
anti_lib_progs/sph_circles.py
anti_lib_progs/sph_saff.py
anti_lib_progs/sph_spiral.py
anti_lib_progs/spiro.py
anti_lib_progs/str_art.py
anti_lib_progs/temcor_dome.py
anti_lib_progs/tri_tiling.py
anti_lib_progs/twister.py
anti_lib_progs/twister_rhomb.py
anti_lib_progs/twister_test.py
antiprism_python.egg-info/PKG-INFO
antiprism_python.egg-info/SOURCES.txt
antiprism_python.egg-info/dependency_links.txt
antiprism_python.egg-info/entry_points.txt
antiprism_python.egg-info/top_level.txt