Metadata-Version: 1.1
Name: antiprism-python
Version: 0.1.3
Summary: Scripts to generate various types of polyhedra
Home-page: https://github.com/antiprism/antiprism_python
Author: Adrian Rossiter
Author-email: adrian@antiprism.com
License: MIT
Keywords: antiprism polyhdron polyhedra
Platform: UNKNOWN
Classifier: Development Status :: 4 - Beta
Classifier: Environment :: Console
Classifier: Intended Audience :: Science/Research
Classifier: Topic :: Scientific/Engineering :: Mathematics
Classifier: Topic :: Scientific/Engineering :: Visualization
Classifier: License :: OSI Approved :: MIT License
Classifier: Programming Language :: Python :: 3 :: Only
